lxgrtgr/__init__.py
lxgrtgr/lxgrtgr.py
lxgrtgr-0.5.75.dist-info/METADATA
lxgrtgr-0.5.75.dist-info/WHEEL
lxgrtgr-0.5.75.dist-info/top_level.txt
lxgrtgr-0.5.75.dist-info/RECORD
