Metadata-Version: 2.4
Name: lxgrtgr
Version: 0.5.75
Summary: Lexicogrammatical tagging and tag counting tool
Home-page: https://github.com/kristopherkyle/LxGrTgr
Author: Kristopher Kyle
Author-email: kristopherkyle1@gmail.com
Classifier: Programming Language :: Python :: 3
Classifier: Operating System :: OS Independent
Requires-Dist: lxgrcounter
Dynamic: author
Dynamic: author-email
Dynamic: classifier
Dynamic: description
Dynamic: description-content-type
Dynamic: home-page
Dynamic: requires-dist
Dynamic: summary
